<?xml version="1.0" encoding="UTF-8" ?>
<IPPhoneInputScreen type="edit" password="yes" defaultIndex="1" Timeout="0" LockIn="no" LocalData="yes" CombineData="PasswordSetting" InputType="1aB">
    <Title showlistcount="yes">Password Setting</Title>
    <Prompt>Current Password:</Prompt>
    <DataID>Combine_PasswordSetting_CurrentPwd</DataID>
    <Default />
    <InputField type="edit" password="yes">
        <Prompt>New Password:</Prompt>
        <DataID>Combine_PasswordSetting_NewPwd</DataID>
        <Default />
    </InputField>
    <InputField type="edit" password="yes">
        <Prompt>Confirm Password:</Prompt>
        <DataID>Combine_PasswordSetting_ConfirmPwd</DataID>
        <Default />
    </InputField>
</IPPhoneInputScreen>
<SoftKey index="1">
    <Label>Save</Label>
    <URI>SoftKey:Submit</URI>
</SoftKey>
<SoftKey index="2">
    <Label />
    <URI />
</SoftKey>
<SoftKey index="3">
    <Label />
    <URI />
</SoftKey>
<SoftKey index="4">
    <Label>Back</Label>
    <URI>SoftKey:Back</URI>
</SoftKey>
